Metadata-Version: 2.1
Name: namespacedict
Version: 0.2.0
Summary: dictionary with fully evaluated keys
Home-page: https://github.com/ntessore/namespacedict
Author: Nicolas Tessore
Author-email: n.tessore@ucl.ac.uk
License: MIT
Platform: UNKNOWN
Classifier: Programming Language :: Python :: 3
Classifier: License :: OSI Approved :: MIT License
Classifier: Operating System :: OS Independent
Requires-Python: >=3.6
Provides-Extra: test
